android_emulator_cleaner/__init__.py
android_emulator_cleaner/__main__.py
android_emulator_cleaner/cli.py
android_emulator_cleaner/core/__init__.py
android_emulator_cleaner/core/adb.py
android_emulator_cleaner/core/avd.py
android_emulator_cleaner/core/cleaner.py
android_emulator_cleaner/models/__init__.py
android_emulator_cleaner/models/types.py
android_emulator_cleaner/ui/__init__.py
android_emulator_cleaner/ui/console.py
android_emulator_cleaner/ui/panels.py
android_emulator_cleaner-1.0.0.dist-info/METADATA
android_emulator_cleaner-1.0.0.dist-info/WHEEL
android_emulator_cleaner-1.0.0.dist-info/entry_points.txt
android_emulator_cleaner-1.0.0.dist-info/licenses/LICENSE
android_emulator_cleaner-1.0.0.dist-info/RECORD
