Metadata-Version: 2.4
Name: android-emulator-cleaner
Version: 1.0.0
Summary: A beautiful terminal-based utility to clean up Android emulator storage without losing your data
Project-URL: Homepage, https://github.com/CanArslanDev/android_emulator_cleaner
Project-URL: Documentation, https://github.com/CanArslanDev/android_emulator_cleaner#readme
Project-URL: Repository, https://github.com/CanArslanDev/android_emulator_cleaner
Project-URL: Issues, https://github.com/CanArslanDev/android_emulator_cleaner/issues
Project-URL: Changelog, https://github.com/CanArslanDev/android_emulator_cleaner/blob/main/CHANGELOG.md
Author: Android Emulator Cleaner Contributors
Maintainer: Android Emulator Cleaner Contributors
License-Expression: MIT
License-File: LICENSE
Keywords: adb,android,avd,cleaner,cli,development,emulator,flutter,storage,terminal
Classifier: Development Status :: 5 - Production/Stable
Classifier: Environment :: Console
Classifier: Intended Audience :: Developers
Classifier: License :: OSI Approved :: MIT License
Classifier: Operating System :: OS Independent
Classifier: Programming Language :: Python :: 3
Classifier: Programming Language :: Python :: 3.10
Classifier: Programming Language :: Python :: 3.11
Classifier: Programming Language :: Python :: 3.12
Classifier: Programming Language :: Python :: 3.13
Classifier: Topic :: Software Development :: Testing
Classifier: Topic :: System :: Systems Administration
Classifier: Topic :: Utilities
Requires-Python: >=3.10
Requires-Dist: questionary>=2.0.0
Requires-Dist: rich>=13.0.0
Provides-Extra: dev
Requires-Dist: mypy>=1.0.0; extra == 'dev'
Requires-Dist: pre-commit>=3.0.0; extra == 'dev'
Requires-Dist: pytest-cov>=4.0.0; extra == 'dev'
Requires-Dist: pytest-mock>=3.10.0; extra == 'dev'
Requires-Dist: pytest>=7.0.0; extra == 'dev'
Requires-Dist: ruff>=0.1.0; extra == 'dev'
